citation_report/__init__.py
citation_report/main.py
citation_report/published_report.py
citation_report/publisher.py
citation_report-0.2.0.dist-info/licenses/LICENSE
citation_report-0.2.0.dist-info/METADATA
citation_report-0.2.0.dist-info/WHEEL
citation_report-0.2.0.dist-info/top_level.txt
citation_report-0.2.0.dist-info/RECORD
