Metadata-Version: 2.4
Name: citation-report
Version: 0.2.0
Summary: Regex formula of Philippine Supreme Court citations in report format, i.e. SCRA, PHIL, OFFG.
Requires-Python: >=3.13
License-File: LICENSE
Requires-Dist: citation-date>=0.2.1
Requires-Dist: pydantic>=2.11.9
Dynamic: license-file
